gridijkstra/__init__.py
gridijkstra/routing.py
gridijkstra-0.1.dist-info/LICENSE
gridijkstra-0.1.dist-info/METADATA
gridijkstra-0.1.dist-info/WHEEL
gridijkstra-0.1.dist-info/top_level.txt
gridijkstra-0.1.dist-info/RECORD
