Metadata-Version: 2.1
Name: gridijkstra
Version: 0.1
Summary: Python package wrapping scipy.sparse.csgraph.dijkstra with a grid-based interface
Home-page: https://github.com/vegardkv/gridijkstra
Author: vegardkv
License: UNKNOWN
Platform: UNKNOWN
Classifier: Programming Language :: Python :: 3
Classifier: License :: OSI Approved :: MIT License
Classifier: Operating System :: OS Independent
Requires-Python: >=3.6
License-File: LICENSE
